ai_sprint/__init__.py
ai_sprint/checks.py
ai_sprint/cli.py
ai_sprint/commit.py
ai_sprint/guidance.py
ai_sprint/policy.py
ai_sprint/pr_creator.py
ai_sprint/preflight.py
ai_sprint/spec_validator.py
ai_sprint/state.py
ai_sprint/submodule.py
ai_sprint/sync_engine.py
ai_sprint/telemetry.py
ai_sprint/trace.py
ai_sprint/visual_generator.py
ai_sprint/commands/__init__.py
ai_sprint/commands/assets.py
ai_sprint/commands/common.py
ai_sprint/commands/plan.py
ai_sprint/commands/sprint.py
ai_sprint/commands/task.py
ai_sprint/commands/utility.py
ai_sprint/commands/governance/__init__.py
ai_sprint/commands/governance/close.py
ai_sprint/commands/governance/commit.py
ai_sprint/commands/governance/engine.py
ai_sprint/commands/governance/preflight.py
ai_sprint/commands/governance/utils.py
ai_sprint/commands/governance/verify.py
ai_sprint/hooks/__init__.py
ai_sprint/schemas/sprint.schema.json
onecoder/agent.py
onecoder/alignment.py
onecoder/api.py
onecoder/api_client.py
onecoder/blackboard.py
onecoder/cli.py
onecoder/config_manager.py
onecoder/constants.py
onecoder/discovery.py
onecoder/distillation.py
onecoder/dspy_config.yaml
onecoder/dspy_utils.py
onecoder/env_manager.py
onecoder/finops_logger.py
onecoder/hooks.py
onecoder/ipc_auth.py
onecoder/issues.py
onecoder/jules_client.py
onecoder/knowledge.py
onecoder/llm.py
onecoder/logger.py
onecoder/metrics.py
onecoder/model_factory.py
onecoder/onboarding.py
onecoder/review.py
onecoder/sessions.py
onecoder/sprint_collector.py
onecoder/sync.py
onecoder/tmux.py
onecoder/tracing.py
onecoder/tracker.py
onecoder/usage_logger.py
onecoder/worktree.py
onecoder/agentic_tool_search/__init__.py
onecoder/agentic_tool_search/dynamic_tool_search.py
onecoder/agentic_tool_search/registry.py
onecoder/agents/__init__.py
onecoder/agents/documentation_agent.py
onecoder/agents/file_reader_agent.py
onecoder/agents/file_writer_agent.py
onecoder/agents/orchestrator_agent.py
onecoder/agents/orchestrator_dspy.py
onecoder/agents/refactoring_agent.py
onecoder-0.0.7.dist-info/METADATA
onecoder-0.0.7.dist-info/WHEEL
onecoder-0.0.7.dist-info/entry_points.txt
onecoder-0.0.7.dist-info/top_level.txt
onecoder-0.0.7.dist-info/RECORD
