Metadata-Version: 2.4
Name: onecoder
Version: 0.0.7
Requires-Python: >=3.11
Requires-Dist: google-adk>=1.22.0
Requires-Dist: google-genai>=1.56.0
Requires-Dist: Authlib
Requires-Dist: pydantic
Requires-Dist: litellm
Requires-Dist: python-dotenv
Requires-Dist: rank-bm25
Requires-Dist: fastapi>=0.104.0
Requires-Dist: uvicorn[standard]>=0.24.0
Requires-Dist: httpx>=0.25.0
Requires-Dist: rich>=13.0.0
Requires-Dist: click>=8.1.0
Requires-Dist: requests>=2.31.0
Requires-Dist: keyring>=24.0.0
Requires-Dist: cryptography>=41.0.0
Requires-Dist: python-frontmatter>=1.0.0
Requires-Dist: pluggy>=1.0.0
Requires-Dist: jsonschema>=4.0.0
Requires-Dist: pytest>=7.4.0
Requires-Dist: pytest-asyncio>=0.21.0
Requires-Dist: respx>=0.21.0
Requires-Dist: twine
Requires-Dist: mlflow>=2.14.0
Requires-Dist: dspy-ai>=2.5.0
Requires-Dist: PyYAML>=6.0.0
Requires-Dist: mcp>=0.1.0
Provides-Extra: tldr
Requires-Dist: tree-sitter==0.21.3; extra == "tldr"
Requires-Dist: tree-sitter-languages>=1.10.0; extra == "tldr"
Provides-Extra: internal
Requires-Dist: textual>=0.50.0; extra == "internal"
Requires-Dist: onecoder-rlm; extra == "internal"
Requires-Dist: onecore; extra == "internal"
